{
  "name": "プロキシマ・ケンタウリ",
  "icon": "ad_astra:/textures/painting/alpha_centauri.png",
  "sortnum": 1,
  "category": "ad_astra:the_hot_planets",
  "pages": [
    {
      "type": "patchouli:text",
      "title": "プロキシマ・ケンタウリ",
      "text": "十分なカロライトを見つけてティア4のロケットを作成すると、この太陽系を離れて新しい太陽系に入ることができるようになります。プロキシマ・ケンタウリで最初に向かう惑星はグラシオです。グラシオは非常に寒いですが、酸素があるため、宇宙服なしで生き延びることができます。"
    },
    {
      "type": "patchouli:text",
      "text": "これは今のところアド・アストラの進行の終わりです。このガイドブックは、さらなるコンテンツが追加されるにつれて拡張されます。アド・アストラをプレイしていただきありがとうございます！"
    }
  ]
}